hw1/prebuilt_gates.v
// 2-input AND
module AND2 (a, b, f);
	input a;
	input b;
	output f;

        // Dataflow verilog style.
	assign f = (a & b);
endmodule

// 2-input OR
module OR2 (a, b, f);
	input a;
	input b;
	output f;

        // Dataflow verilog style.
	assign f = (a | b);
endmodule

// 2-input NAND
module NAND2 (a, b, f);
	input a;
	input b;
	output f;

        // Dataflow verilog style.
	assign f = ~(a & b);
endmodule

// 2-input NOR
module NOR2 (a, b, f);
	input a;
	input b;
	output f;

        // Dataflow verilog style.
	assign f = ~(a | b);
endmodule

// inverter (NOT gate)
module INV (a, f);
	input a;
	output f;

        // Dataflow verilog style.
	assign f = ~a;
endmodule

hw1/circuit1.v
//Nikhil G. Khatu (HW#1)---> modified modules
// Circuit #1 implemented in structural verilog style.
module circuit1_structural (a, b, c, f);
	input a, b, c;
	output f;
	wire node1;

        // Structural verilog style.
	OR2 u1 (a, b, node1);
	NAND2 u2 (node1, c, f);
	
	
endmodule

// Circuit #1 implemented in dataflow verilog style.
module circuit1_dataflow (a, b, c, f);
	input a, b, c;
	output f;
	wire node1;

        // Dataflow verilog style.
	assign node1 = (a | b)
	assign f = ~(node1 & c);
	
endmodule

2hw1/test.v
`timescale 1 ns / 100 ps

module test_fixture;
	reg done;
	reg [2:0] test_input;
	wire f1, f2;

	initial
	begin
	   $dumpfile("circuit1.vcd"); // save waveforms in this file
	   $dumpvars;                 // saves all waveforms

	   // initialize done signal to 0
	   done = 1'b0;

	   // test 000 case
	   test_input[2] = 0;
	   test_input[1] = 0;
	   test_input[0] = 0;

	   // wait 5 ns, then test 001 case
	   #5 
	   test_input[2] = 0;
	   test_input[1] = 0;
	   test_input[0] = 1;

	   // wait another 5 ns, then test 010 case
	   #5
	   test_input[2] = 0;
	   test_input[1] = 1;
	   test_input[0] = 0;

	   // wait another 5 ns, then test 011 case
	   #5
	   test_input[2] = 0;
	   test_input[1] = 1;
	   test_input[0] = 1;

	   // wait another 5 ns, then test 100 case
	   #5
	   test_input[2] = 1;
	   test_input[1] = 0;
	   test_input[0] = 0;

	   // wait another 5 ns, then test 101 case
	   #5
	   test_input[2] = 1;
	   test_input[1] = 0;
	   test_input[0] = 1;

	   // wait another 5 ns, then test 110 case
	   #5
	   test_input[2] = 1;
	   test_input[1] = 1;
	   test_input[0] = 0;

	   // wait another 5 ns, then test 111 case
	   #5
	   test_input[2] = 1;
	   test_input[1] = 1;
	   test_input[0] = 1;


	   // Bogus kluge to extend simulation time for better viewing.
	   #5 done = 1'b1;

	   $finish;       // finished with simulation
	end
	

	// Instantiate two copies of Circuit #1 - but different implementations.
	circuit1_structural u3 (test_input[2], test_input[1], test_input[0], f1);
	circuit1_dataflow u4 (test_input[2], test_input[1], test_input[0], f2);

endmodule	// test_fixture

hw1/circuit1.vcd
$date
    Sep  3, 2006  16:37:19
$end
$version
    Tool:	VERILOG-XL	05.10.003-s
$end
$timescale
     100ps
$end

$scope module test_fixture $end
$var reg       1 !    done  $end
$var reg       3 "    test_input [2:0] $end
$var wire      1 #    f1  $end
$var wire      1 $    f2  $end

$scope module u3 $end
$var wire      1 %    a  $end
$var wire      1 &    b  $end
$var wire      1 '    c  $end
$var wire      1 #    f  $end
$var wire      1 (    node1  $end

$scope module u2 $end
$var wire      1 (    a  $end
$var wire      1 '    b  $end
$var wire      1 #    f  $end
$upscope $end


$scope module u1 $end
$var wire      1 %    a  $end
$var wire      1 &    b  $end
$var wire      1 (    f  $end
$upscope $end

$upscope $end


$scope module u4 $end
$var wire      1 )    a  $end
$var wire      1 *    b  $end
$var wire      1 +    c  $end
$var wire      1 $    f  $end
$var wire      1 ,    node1  $end
$upscope $end

$upscope $end


$scope module NAND2 $end
$var wire      1 -    a  $end
$var wire      1 .    b  $end
$var wire      1 /    f  $end
$upscope $end


$scope module NOR2 $end
$var wire      1 0    a  $end
$var wire      1 1    b  $end
$var wire      1 2    f  $end
$upscope $end


$scope module INV $end
$var wire      1 3    a  $end
$var wire      1 4    f  $end
$upscope $end

$enddefinitions $end
$dumpvars
0!
b000 "
0#
0$
0%
0&
0'
0(
0)
0*
0+
z,
z-
z.
x/
z0
z1
x2
z3
x4
$end
#50
b001 "
1+
1'
1$
1#
#100
b011 "
b010 "
1*
1&
0+
0'
0$
0#
#150
b011 "
1+
1'
1$
1#
#200
b111 "
b101 "
b100 "
1)
1%
0*
0&
0+
0'
0$
0#
#250
b101 "
1+
1'
1$
1#
#300
b111 "
b110 "
1*
1&
0+
0'
1(
#350
b111 "
1+
1'
#400
1!
