hw2/prebuilt_gates.v
//Nikhil G. Khatu
//HW #2

// 2-input AND
module AND2 (a, b, f);
	input a;
	input b;
	output f;

        // Dataflow verilog style.
	assign f = (a & b);
endmodule

// 2-input OR
module OR2 (a, b, f);
	input a;
	input b;
	output f;

        // Dataflow verilog style.
	assign f = (a | b);
endmodule

// 2-input NAND
module NAND2 (a, b, f);
	input a;
	input b;
	output f;

        // Dataflow verilog style.
	assign f = ~(a & b);
endmodule

// 2-input NOR
module NOR2 (a, b, f);
	input a;
	input b;
	output f;

        // Dataflow verilog style.
	assign f = ~(a | b);
endmodule

// inverter (NOT gate)
module INV (a, f);
	input a;
	output f;

        // Dataflow verilog style.
	assign f = ~a;
endmodule

// 3-input NOR
module NOR3 (a, b, c, f);
	input a;
	input b;
	input c;
	output f;
	
	//Dataflow verilog style.
	assign f = ~(a | b | c);
endmodule

// 3-input NAND
module NAND3 (a, b, c, f);
	input a;
	input b;
	input c;
	output f;
	
	//Dataflow verilog style.
	assign f = ~(a & b & c);
endmodule

// 3-input OR
module OR3 (a, b, c, f);
	input a;
	input b;
	input c;
	output f;
	
	//Dataflow verilog style.
	assign f = (a | b | c);
endmodule

// 3-input AND
module AND3 (a, b, c, f);
	input a;
	input b;
	input c;
	output f;
	
	//Dataflow verilog style.
	assign f = (a & b & c);
endmodule

// 4-input OR
module OR4 (a, b, c, d, f);
	input a;
	input b;
	input c;
	input d;
	output f;
	
	//Dataflow verilog style.
	assign f = (a | b | c | d);
endmodule

// 4-input AND
module AND4 (a, b, c, d, f);
	input a;
	input b;
	input c;
	input d;
	output f;
	
	//Dataflow verilog style.
	assign f = (a & b & c & d);
endmodule

hw2/circuit1.v
//Nikhil G. Khatu
//HW #2

// #4 implemented in dataflow verilog style.
module parity_dataflow (x, y, z, f);
	input x, y, z;
	output f;
	wire node1;
	wire node2;
	wire node3;
	wire node4;

        // Dataflow verilog style.
	assign node1 = (~x & ~y & z);
	assign node2 = (~x & y & ~z);
	assign node3 = (x & ~y & ~z);
	assign node4 = (x & y & z);
	assign f = (node1 | node2 | node3 | node4);
endmodule

// #4 implemented in structural verilog style.
module parity_structural (x, y, z, f);
	input x, y, z;
	output f;
	wire node1;
	wire node2;
	wire node3;
	wire node4;

        // Structural verilog style.
	AND3 u1 (~x, ~y, z, node1);
	AND3 u2 (~x, y, ~z, node2);
	AND3 u3 (x, ~y, ~z, node3);
	AND3 u4 (x, y, z, node4);
	OR4 u5 (node1, node2, node3, node4, f);
endmodule

hw2/test.v
//Nikhil G. Khatu
// HW #2
`timescale 1 ns / 100 ps

module test_fixture;
	reg done;
	reg [2:0] test_input;
	wire f1, f2;

	initial
	begin
	   $dumpfile("circuit1.vcd"); // save waveforms in this file
	   $dumpvars;                 // saves all waveforms

	   // initialize done signal to 0
	   done = 1'b0;

	   // test 000 case
	   test_input[2] = 0;
	   test_input[1] = 0;
	   test_input[0] = 0;

	   // wait 5 ns, then test 001 case
	   #5 
	   test_input[2] = 0;
	   test_input[1] = 0;
	   test_input[0] = 1;

	   // wait another 5 ns, then test 010 case
	   #5
	   test_input[2] = 0;
	   test_input[1] = 1;
	   test_input[0] = 0;

	   // wait another 5 ns, then test 011 case
	   #5
	   test_input[2] = 0;
	   test_input[1] = 1;
	   test_input[0] = 1;

	   // wait another 5 ns, then test 100 case
	   #5
	   test_input[2] = 1;
	   test_input[1] = 0;
	   test_input[0] = 0;

	   // wait another 5 ns, then test 101 case
	   #5
	   test_input[2] = 1;
	   test_input[1] = 0;
	   test_input[0] = 1;

	   // wait another 5 ns, then test 110 case
	   #5
	   test_input[2] = 1;
	   test_input[1] = 1;
	   test_input[0] = 0;

	   // wait another 5 ns, then test 111 case
	   #5
	   test_input[2] = 1;
	   test_input[1] = 1;
	   test_input[0] = 1;


	   // Bogus kluge to extend simulation time for better viewing.
	   #5 done = 1'b1;

	   $finish;       // finished with simulation
	end
	

	// Instantiate two copies of Circuit #1 - but different implementations.
	parity_structural u3 (test_input[2], test_input[1], test_input[0], f1);
	parity_dataflow u4 (test_input[2], test_input[1], test_input[0], f2);

endmodule	// test_fixture

hw2/circuit1.vcd
$date
    Jan 29, 2007  12:30:53
$end
$version
    Tool:	VERILOG-XL	05.10.003-s
$end
$timescale
     100ps
$end

$scope module test_fixture $end
$var reg       1 !    done  $end
$var reg       3 "    test_input [2:0] $end
$var wire      1 #    f1  $end
$var wire      1 $    f2  $end

$scope module u3 $end
$var wire      1 %    x  $end
$var wire      1 &    y  $end
$var wire      1 '    z  $end
$var wire      1 #    f  $end
$var wire      1 (    node1  $end
$var wire      1 )    node2  $end
$var wire      1 *    node3  $end
$var wire      1 +    node4  $end

$scope module u1 $end
$var wire      1 ,    a  $end
$var wire      1 -    b  $end
$var wire      1 '    c  $end
$var wire      1 (    f  $end
$upscope $end


$scope module u2 $end
$var wire      1 .    a  $end
$var wire      1 &    b  $end
$var wire      1 /    c  $end
$var wire      1 )    f  $end
$upscope $end


$scope module u3 $end
$var wire      1 %    a  $end
$var wire      1 0    b  $end
$var wire      1 1    c  $end
$var wire      1 *    f  $end
$upscope $end


$scope module u4 $end
$var wire      1 %    a  $end
$var wire      1 &    b  $end
$var wire      1 '    c  $end
$var wire      1 +    f  $end
$upscope $end


$scope module u5 $end
$var wire      1 (    a  $end
$var wire      1 )    b  $end
$var wire      1 *    c  $end
$var wire      1 +    d  $end
$var wire      1 #    f  $end
$upscope $end

$upscope $end


$scope module u4 $end
$var wire      1 2    x  $end
$var wire      1 3    y  $end
$var wire      1 4    z  $end
$var wire      1 $    f  $end
$var wire      1 5    node1  $end
$var wire      1 6    node2  $end
$var wire      1 7    node3  $end
$var wire      1 8    node4  $end
$upscope $end

$upscope $end


$scope module AND2 $end
$var wire      1 9    a  $end
$var wire      1 :    b  $end
$var wire      1 ;    f  $end
$upscope $end


$scope module OR2 $end
$var wire      1 <    a  $end
$var wire      1 =    b  $end
$var wire      1 >    f  $end
$upscope $end


$scope module NAND2 $end
$var wire      1 ?    a  $end
$var wire      1 @    b  $end
$var wire      1 A    f  $end
$upscope $end


$scope module NOR2 $end
$var wire      1 B    a  $end
$var wire      1 C    b  $end
$var wire      1 D    f  $end
$upscope $end


$scope module INV $end
$var wire      1 E    a  $end
$var wire      1 F    f  $end
$upscope $end


$scope module NOR3 $end
$var wire      1 G    a  $end
$var wire      1 H    b  $end
$var wire      1 I    c  $end
$var wire      1 J    f  $end
$upscope $end


$scope module NAND3 $end
$var wire      1 K    a  $end
$var wire      1 L    b  $end
$var wire      1 M    c  $end
$var wire      1 N    f  $end
$upscope $end


$scope module OR3 $end
$var wire      1 O    a  $end
$var wire      1 P    b  $end
$var wire      1 Q    c  $end
$var wire      1 R    f  $end
$upscope $end


$scope module AND4 $end
$var wire      1 S    a  $end
$var wire      1 T    b  $end
$var wire      1 U    c  $end
$var wire      1 V    d  $end
$var wire      1 W    f  $end
$upscope $end

$enddefinitions $end
$dumpvars
0!
b000 "
0#
0$
0%
0&
0'
0(
0)
0*
0+
1,
1-
1.
1/
10
11
02
03
04
05
06
07
08
z9
z:
x;
z<
z=
x>
z?
z@
xA
zB
zC
xD
zE
xF
zG
zH
zI
xJ
zK
zL
zM
xN
zO
zP
zQ
xR
zS
zT
zU
zV
xW
$end
#50
b001 "
14
1'
15
01
0/
1(
1$
1#
#100
b011 "
b010 "
13
1&
04
0'
05
00
0-
16
11
1/
0(
1)
#150
b011 "
14
1'
06
01
0/
0$
0)
0#
#200
b111 "
b101 "
b100 "
12
1%
03
0&
04
0'
0.
0,
10
1-
17
11
1/
1$
1*
1#
#250
b101 "
14
1'
07
01
0/
0$
0*
0#
#300
b111 "
b110 "
13
1&
04
0'
00
0-
11
1/
#350
b111 "
14
1'
18
1+
01
0/
1$
1#
#400
1!
