hw3/Verilog/Decoder.v
module Two_to_Four_decoder (G, A, B, yo, y1, y2, y3) ;
	input G, A, B ;
	output yo, y1, y2, y3 ;
	
	assign yo = (G & ~A & ~B) ;
	assign y1 = (G & A & ~B) ;
	assign y2 = (G & ~A & B) ;
	assign y3 = (G & A & B) ;
endmodule

module Four_to_Sixteen_decoder (G, n3, n2, n1, n0, dec0, dec1, dec2, dec3, dec4, dec5, dec6, dec7, dec8, dec9, dec10, dec11, dec12, dec13, dec14, dec15) ;
	input G ;
	input n3, n2, n1, n0 ;
	output dec0, dec1, dec2, dec3, dec4, dec5, dec6, dec7, dec8, dec9, dec10, dec11, dec12, dec13, dec14, dec15 ;
	wire enable1, enable2, enable3, enable4 ;
	wire out0, out1, out2, out3, out4, out5, out6, out7, out8, out9, out10, out11, out12, out13, out14, out15 ;
	
	Two_to_Four_decoder u1 (G, n2, n3, enable1, enable2, enable3, enable4) ;
	
	Two_to_Four_decoder u2 (enable1, n0, n1, out0, out1, out2, out3) ;
	assign dec0 = out0 ;
	assign dec1 = out1 ;
	assign dec2 = out2 ;
	assign dec3 = out3 ;
	
	Two_to_Four_decoder u3 (enable2, n0, n1, out4, out5, out6, out7) ;
	assign dec4 = out4 ;
	assign dec5 = out5 ;
	assign dec6 = out6 ;
	assign dec7 = out7 ;
	
	Two_to_Four_decoder u4 (enable3, n0, n1, out8, out9, out10, out11) ;
	assign dec8 = out8 ;
	assign dec9 = out9 ;
	assign dec10 = out10 ;
	assign dec11 = out11 ;
	
	Two_to_Four_decoder u5 (enable4, n0, n1, out12, out13, out14, out15) ;
	assign dec12 = out12 ;
	assign dec13 = out13 ;
	assign dec14 = out14 ;
	assign dec15 = out15 ;
endmodule

hw3/Verilog/test.v
`timescale 1 ns / 100 ps

module test_fixture;
	reg done;
	reg [3:0] test_input;
	wire dec0, dec1, dec2, dec3, dec4, dec5, dec6, dec7, dec8, dec9, dec10, dec11, dec12, dec13, dec14, dec15;
	wire G ;
	assign G = 1 ;
	initial
	begin
	   $dumpfile("dec4to16.vcd"); // save waveforms in this file
	   $dumpvars;                 // saves all waveforms

	   // initialize done signal to 0
	   done = 1'b0;

	   // test 0000 case
	   test_input[3] = 0;
	   test_input[2] = 0;
	   test_input[1] = 0;
	   test_input[0] = 0;
	   // wait 5 ns, then test 001 case
	   #5 
	   test_input[3] = 0;
	   test_input[2] = 0;
	   test_input[1] = 0;
	   test_input[0] = 1;
	   // wait 5 ns, then test 001 case
	   #5 
	   test_input[3] = 0;
	   test_input[2] = 0;
	   test_input[1] = 1;
	   test_input[0] = 0;
	   // wait 5 ns, then test 001 case
	   #5 
	   test_input[3] = 0;
	   test_input[2] = 0;
	   test_input[1] = 1;
	   test_input[0] = 1;
	   // wait 5 ns, then test 001 case
	   #5 
	   test_input[3] = 0;
	   test_input[2] = 1;
	   test_input[1] = 0;
	   test_input[0] = 0;
	   // wait 5 ns, then test 001 case
	   #5 
	   test_input[3] = 0;
	   test_input[2] = 1;
	   test_input[1] = 0;
	   test_input[0] = 1;
	   // wait 5 ns, then test 001 case
	   #5 
	   test_input[3] = 0;
	   test_input[2] = 1;
	   test_input[1] = 1;
	   test_input[0] = 0;
	   // wait 5 ns, then test 001 case
	   #5 
	   test_input[3] = 0;
	   test_input[2] = 1;
	   test_input[1] = 1;
	   test_input[0] = 1;
	   
	    // test 0000 case
	   test_input[3] = 1;
	   test_input[2] = 0;
	   test_input[1] = 0;
	   test_input[0] = 0;
	   // wait 5 ns, then test 001 case
	   #5 
	   test_input[3] = 1;
	   test_input[2] = 0;
	   test_input[1] = 0;
	   test_input[0] = 1;
	   // wait 5 ns, then test 001 case
	   #5 
	   test_input[3] = 1;
	   test_input[2] = 0;
	   test_input[1] = 1;
	   test_input[0] = 0;
	   // wait 5 ns, then test 001 case
	   #5 
	   test_input[3] = 1;
	   test_input[2] = 0;
	   test_input[1] = 1;
	   test_input[0] = 1;
	   // wait 5 ns, then test 001 case
	   #5 
	   test_input[3] = 1;
	   test_input[2] = 1;
	   test_input[1] = 0;
	   test_input[0] = 0;
	   // wait 5 ns, then test 001 case
	   #5 
	   test_input[3] = 1;
	   test_input[2] = 1;
	   test_input[1] = 0;
	   test_input[0] = 1;
	   // wait 5 ns, then test 001 case
	   #5 
	   test_input[3] = 1;
	   test_input[2] = 1;
	   test_input[1] = 1;
	   test_input[0] = 0;
	   // wait 5 ns, then test 001 case
	   #5 
	   test_input[3] = 1;
	   test_input[2] = 1;
	   test_input[1] = 1;
	   test_input[0] = 1;
	   

	   // Bogus kluge to extend simulation time for better viewing.
	   #5 done = 1'b1;

	   $finish;       // finished with simulation
	end
	

	// Instantiate test decoder
	 Four_to_Sixteen_decoder u6 (G , test_input[3], test_input[2], test_input[1], test_input[0], dec0, dec1, dec2, dec3, dec4, dec5, dec6, dec7, dec8, dec9, dec10, dec11, dec12, dec13, dec14, dec15);
	

endmodule	// test_fixture

hw3/Verilog/dec4to16.vcd
$date
    Feb 28, 2007  12:13:55
$end
$version
    Tool:	VERILOG-XL	05.10.003-s
$end
$timescale
     100ps
$end

$scope module test_fixture $end
$var reg       1 !    done  $end
$var reg       4 "    test_input [3:0] $end
$var wire      1 #    dec0  $end
$var wire      1 $    dec1  $end
$var wire      1 %    dec2  $end
$var wire      1 &    dec3  $end
$var wire      1 '    dec4  $end
$var wire      1 (    dec5  $end
$var wire      1 )    dec6  $end
$var wire      1 *    dec7  $end
$var wire      1 +    dec8  $end
$var wire      1 ,    dec9  $end
$var wire      1 -    dec10  $end
$var wire      1 .    dec11  $end
$var wire      1 /    dec12  $end
$var wire      1 0    dec13  $end
$var wire      1 1    dec14  $end
$var wire      1 2    dec15  $end
$var wire      1 3    G  $end

$scope module u6 $end
$var wire      1 3    G  $end
$var wire      1 4    n3  $end
$var wire      1 5    n2  $end
$var wire      1 6    n1  $end
$var wire      1 7    n0  $end
$var wire      1 #    dec0  $end
$var wire      1 $    dec1  $end
$var wire      1 %    dec2  $end
$var wire      1 &    dec3  $end
$var wire      1 '    dec4  $end
$var wire      1 (    dec5  $end
$var wire      1 )    dec6  $end
$var wire      1 *    dec7  $end
$var wire      1 +    dec8  $end
$var wire      1 ,    dec9  $end
$var wire      1 -    dec10  $end
$var wire      1 .    dec11  $end
$var wire      1 /    dec12  $end
$var wire      1 0    dec13  $end
$var wire      1 1    dec14  $end
$var wire      1 2    dec15  $end
$var wire      1 8    enable1  $end
$var wire      1 9    enable2  $end
$var wire      1 :    enable3  $end
$var wire      1 ;    enable4  $end
$var wire      1 <    out0  $end
$var wire      1 =    out1  $end
$var wire      1 >    out2  $end
$var wire      1 ?    out3  $end
$var wire      1 @    out4  $end
$var wire      1 A    out5  $end
$var wire      1 B    out6  $end
$var wire      1 C    out7  $end
$var wire      1 D    out8  $end
$var wire      1 E    out9  $end
$var wire      1 F    out10  $end
$var wire      1 G    out11  $end
$var wire      1 H    out12  $end
$var wire      1 I    out13  $end
$var wire      1 J    out14  $end
$var wire      1 K    out15  $end

$scope module u1 $end
$var wire      1 3    G  $end
$var wire      1 5    A  $end
$var wire      1 4    B  $end
$var wire      1 8    yo  $end
$var wire      1 9    y1  $end
$var wire      1 :    y2  $end
$var wire      1 ;    y3  $end
$upscope $end


$scope module u2 $end
$var wire      1 8    G  $end
$var wire      1 7    A  $end
$var wire      1 6    B  $end
$var wire      1 <    yo  $end
$var wire      1 =    y1  $end
$var wire      1 >    y2  $end
$var wire      1 ?    y3  $end
$upscope $end


$scope module u3 $end
$var wire      1 9    G  $end
$var wire      1 7    A  $end
$var wire      1 6    B  $end
$var wire      1 @    yo  $end
$var wire      1 A    y1  $end
$var wire      1 B    y2  $end
$var wire      1 C    y3  $end
$upscope $end


$scope module u4 $end
$var wire      1 :    G  $end
$var wire      1 7    A  $end
$var wire      1 6    B  $end
$var wire      1 D    yo  $end
$var wire      1 E    y1  $end
$var wire      1 F    y2  $end
$var wire      1 G    y3  $end
$upscope $end


$scope module u5 $end
$var wire      1 ;    G  $end
$var wire      1 7    A  $end
$var wire      1 6    B  $end
$var wire      1 H    yo  $end
$var wire      1 I    y1  $end
$var wire      1 J    y2  $end
$var wire      1 K    y3  $end
$upscope $end

$upscope $end

$upscope $end

$enddefinitions $end
$dumpvars
0!
b0000 "
1#
0$
0%
0&
0'
0(
0)
0*
0+
0,
0-
0.
0/
00
01
02
13
04
05
06
07
18
09
0:
0;
1<
0=
0>
0?
0@
0A
0B
0C
0D
0E
0F
0G
0H
0I
0J
0K
$end
#50
b0001 "
17
1=
0<
1$
0#
#100
b0011 "
b0010 "
16
07
0=
1>
0$
1%
#150
b0011 "
17
1?
0>
1&
0%
#200
b0111 "
b0101 "
b0100 "
15
06
07
19
08
0?
1@
0&
1'
#250
b0101 "
17
1A
0@
1(
0'
#300
b0111 "
b0110 "
16
07
0A
1B
0(
1)
#350
b0111 "
b1111 "
b1011 "
b1001 "
b1000 "
14
05
06
09
1:
0B
1D
0)
1+
#400
b1001 "
17
1E
0D
1,
0+
#450
b1011 "
b1010 "
16
07
0E
1F
0,
1-
#500
b1011 "
17
1G
0F
1.
0-
#550
b1111 "
b1101 "
b1100 "
15
06
07
1;
0:
0G
1H
0.
1/
#600
b1101 "
17
1I
0H
10
0/
#650
b1111 "
b1110 "
16
07
0I
1J
00
11
#700
b1111 "
17
1K
0J
12
01
#750
1!
