project2/prebuilt_gates.v
//Nikhil G. Khatu
//E HW #2
// 3/23/07

// 2-input AND
module AND2 (a, b, f);
	input a;
	input b;
	output f;

        // Dataflow verilog style.
	assign f = (a & b);
endmodule

// 2-input OR
module OR2 (a, b, f);
	input a;
	input b;
	output f;

        // Dataflow verilog style.
	assign f = (a | b);
endmodule

// 2-input NAND
module NAND2 (a, b, f);
	input a;
	input b;
	output f;

        // Dataflow verilog style.
	assign f = ~(a & b);
endmodule

// 2-input NOR
module NOR2 (a, b, f);
	input a;
	input b;
	output f;

        // Dataflow verilog style.
	assign f = ~(a | b);
endmodule

// 2-input XOR
module XOR2 (a, b, f);
	input a;
	input b;
	output f;

        // Dataflow verilog style.
	assign f = ((~a & b) | (a & ~b));
endmodule

// inverter (NOT gate)
module INV (a, f);
	input a;
	output f;

        // Dataflow verilog style.
	assign f = ~a;
endmodule

// 3-input NOR
module NOR3 (a, b, c, f);
	input a;
	input b;
	input c;
	output f;
	
	//Dataflow verilog style.
	assign f = ~(a | b | c);
endmodule

// 3-input NAND
module NAND3 (a, b, c, f);
	input a;
	input b;
	input c;
	output f;
	
	//Dataflow verilog style.
	assign f = ~(a & b & c);
endmodule

// 3-input OR
module OR3 (a, b, c, f);
	input a;
	input b;
	input c;
	output f;
	
	//Dataflow verilog style.
	assign f = (a | b | c);
endmodule

// 3-input AND
module AND3 (a, b, c, f);
	input a;
	input b;
	input c;
	output f;
	
	//Dataflow verilog style.
	assign f = (a & b & c);
endmodule

// 4-input OR
module OR4 (a, b, c, d, f);
	input a;
	input b;
	input c;
	input d;
	output f;
	
	//Dataflow verilog style.
	assign f = (a | b | c | d);
endmodule

// 4-input AND
module AND4 (a, b, c, d, f);
	input a;
	input b;
	input c;
	input d;
	output f;
	
	//Dataflow verilog style.
	assign f = (a & b & c & d);
endmodule

// 4 to 1 one bit MUX
module MUX4 (EN, I3, I2, I1, I0, S1, S0, Y);
	input EN;
	input I3;
	input I2;
	input I1;
	input I0;
	input S1;
	input S0;
	output Y;
	wire select0;
	wire select1;
	wire select2;
	wire select3;
	
	AND4 u1 (EN, I0, ~S1, ~S0, select0);
	AND4 u2 (EN, I1, ~S1, S0, select1);
	AND4 u3 (EN, I2, S1, ~S0, select2);
	AND4 u4 (EN, I3, S1, S0, select3);
	OR4 u5 (select0, select1, select2, select3, Y);
endmodule

2hw1/circuit1.v
// Nikhil G. Khatu HW #1  Exercise E
// Circuit #1 implemented in structural verilog style.
module circuit1_structural (a, b, c, f);
	input a, b, c;
	output f;
	wire node1;

        // Structural verilog style.
	NAND2 u1 (a, b, node1);
	NAND2 u2 (node1, c, f);
	
endmodule

// Circuit #1 implemented in dataflow verilog style.
module circuit1_dataflow (a, b, c, f);
	input a, b, c;
	output f;
	wire node1;

        // Dataflow verilog style.
	
	assign node1 = ~(a & b);
	assign f = ~(node1 &c) ;
endmodule

2hw1/test.v
`timescale 1 ns / 100 ps

module test_fixture;
	reg done;
	reg [2:0] test_input;
	wire f1, f2;

	initial
	begin
	   $dumpfile("circuit1.vcd"); // save waveforms in this file
	   $dumpvars;                 // saves all waveforms

	   // initialize done signal to 0
	   done = 1'b0;

	   // test 000 case
	   test_input[2] = 0;
	   test_input[1] = 0;
	   test_input[0] = 0;

	   // wait 5 ns, then test 001 case
	   #5 
	   test_input[2] = 0;
	   test_input[1] = 0;
	   test_input[0] = 1;

	   // wait another 5 ns, then test 010 case
	   #5
	   test_input[2] = 0;
	   test_input[1] = 1;
	   test_input[0] = 0;

	   // wait another 5 ns, then test 011 case
	   #5
	   test_input[2] = 0;
	   test_input[1] = 1;
	   test_input[0] = 1;

	   // wait another 5 ns, then test 100 case
	   #5
	   test_input[2] = 1;
	   test_input[1] = 0;
	   test_input[0] = 0;

	   // wait another 5 ns, then test 101 case
	   #5
	   test_input[2] = 1;
	   test_input[1] = 0;
	   test_input[0] = 1;

	   // wait another 5 ns, then test 110 case
	   #5
	   test_input[2] = 1;
	   test_input[1] = 1;
	   test_input[0] = 0;

	   // wait another 5 ns, then test 111 case
	   #5
	   test_input[2] = 1;
	   test_input[1] = 1;
	   test_input[0] = 1;


	   // Bogus kluge to extend simulation time for better viewing.
	   #5 done = 1'b1;

	   $finish;       // finished with simulation
	end
	

	// Instantiate two copies of Circuit #1 - but different implementations.
	circuit1_structural u3 (test_input[2], test_input[1], test_input[0], f1);
	circuit1_dataflow u4 (test_input[2], test_input[1], test_input[0], f2);

endmodule	// test_fixture

2hw1/circuit1.vcd
$date
    Jan 10, 2007  15:18:15
$end
$version
    Tool:	VERILOG-XL	05.60.001-p
$end
$timescale
     100ps
$end

$scope module test_fixture $end
$var reg       1 !    done  $end
$var reg       3 "    test_input [2:0] $end
$var wire      1 #    f1  $end
$var wire      1 $    f2  $end

$scope module u3 $end
$var wire      1 %    a  $end
$var wire      1 &    b  $end
$var wire      1 '    c  $end
$var wire      1 #    f  $end
$var wire      1 (    node1  $end

$scope module u1 $end
$var wire      1 %    a  $end
$var wire      1 &    b  $end
$var wire      1 (    f  $end
$upscope $end


$scope module u2 $end
$var wire      1 (    a  $end
$var wire      1 '    b  $end
$var wire      1 #    f  $end
$upscope $end

$upscope $end


$scope module u4 $end
$var wire      1 )    a  $end
$var wire      1 *    b  $end
$var wire      1 +    c  $end
$var wire      1 $    f  $end
$var wire      1 ,    node1  $end
$upscope $end

$upscope $end


$scope module AND2 $end
$var wire      1 -    a  $end
$var wire      1 .    b  $end
$var wire      1 /    f  $end
$upscope $end


$scope module OR2 $end
$var wire      1 0    a  $end
$var wire      1 1    b  $end
$var wire      1 2    f  $end
$upscope $end


$scope module NOR2 $end
$var wire      1 3    a  $end
$var wire      1 4    b  $end
$var wire      1 5    f  $end
$upscope $end


$scope module INV $end
$var wire      1 6    a  $end
$var wire      1 7    f  $end
$upscope $end

$enddefinitions $end
$dumpvars
0!
b000 "
1#
1$
0%
0&
0'
1(
0)
0*
0+
1,
z-
z.
x/
z0
z1
x2
z3
z4
x5
z6
x7
$end
#50
b001 "
1+
1'
0$
0#
#100
b011 "
b010 "
1*
1&
0+
0'
1$
1#
#150
b011 "
1+
1'
0$
0#
#200
b111 "
b101 "
b100 "
1)
1%
0*
0&
0+
0'
1$
1#
#250
b101 "
1+
1'
0$
0#
#300
b111 "
b110 "
1*
1&
0+
0'
0,
0(
1$
1#
#350
b111 "
1+
1'
#400
1!
